fxn/__init__.py
fxn/client.py
fxn/compile.py
fxn/function.py
fxn/logging.py
fxn/sandbox.py
fxn/version.py
fxn/beta/__init__.py
fxn/beta/client.py
fxn/beta/metadata.py
fxn/beta/cli/__init__.py
fxn/beta/cli/llm.py
fxn/beta/cli/mcp.py
fxn/beta/llm/__init__.py
fxn/beta/llm/server.py
fxn/beta/services/__init__.py
fxn/beta/services/prediction.py
fxn/beta/services/remote.py
fxn/c/__init__.py
fxn/c/configuration.py
fxn/c/fxnc.py
fxn/c/map.py
fxn/c/prediction.py
fxn/c/predictor.py
fxn/c/stream.py
fxn/c/value.py
fxn/cli/__init__.py
fxn/cli/auth.py
fxn/cli/compile.py
fxn/cli/misc.py
fxn/cli/predictions.py
fxn/cli/predictors.py
fxn/cli/sources.py
fxn/lib/__init__.py
fxn/lib/linux/arm64/libFunction.so
fxn/lib/linux/x86_64/libFunction.so
fxn/lib/macos/arm64/Function.dylib
fxn/lib/macos/x86_64/Function.dylib
fxn/lib/windows/arm64/Function.dll
fxn/lib/windows/x86_64/Function.dll
fxn/services/__init__.py
fxn/services/prediction.py
fxn/services/predictor.py
fxn/services/user.py
fxn/types/__init__.py
fxn/types/dtype.py
fxn/types/prediction.py
fxn/types/predictor.py
fxn/types/user.py
fxn-0.0.55.dist-info/licenses/LICENSE
fxn-0.0.55.dist-info/METADATA
fxn-0.0.55.dist-info/WHEEL
fxn-0.0.55.dist-info/entry_points.txt
fxn-0.0.55.dist-info/top_level.txt
fxn-0.0.55.dist-info/RECORD
