Metadata-Version: 2.4
Name: fxn
Version: 0.0.55
Summary: Run prediction functions locally in Python. Register at https://fxn.ai.
Author-email: "NatML Inc." <hi@fxn.ai>
License:                                  Apache License
Project-URL: Homepage, https://fxn.ai
Project-URL: Documentation, https://docs.fxn.ai
Project-URL: Source, https://github.com/fxnai/fxn
Project-URL: Changelog, https://github.com/fxnai/fxn/blob/main/Changelog.md
Classifier: Programming Language :: Python :: 3
Classifier: License :: OSI Approved :: Apache Software License
Classifier: Operating System :: OS Independent
Classifier: Topic :: Scientific/Engineering :: Image Recognition
Classifier: Topic :: Software Development :: Libraries
Requires-Python: >=3.10
License-File: LICENSE
Requires-Dist: numpy
Requires-Dist: pillow
Requires-Dist: pydantic>=2.0
Requires-Dist: requests
Requires-Dist: rich
Requires-Dist: typer
Dynamic: license-file
